prologix_gpib_async/__init__.py
prologix_gpib_async/_version.py
prologix_gpib_async/ip_connection.py
prologix_gpib_async/prologix_gpib_async.py
prologix_gpib_async/prologix_gpib_base.py
prologix_gpib_async/prologix_gpib_ethernet.py
prologix_gpib_async-1.5.0.dist-info/licenses/LICENSE
prologix_gpib_async-1.5.0.dist-info/METADATA
prologix_gpib_async-1.5.0.dist-info/WHEEL
prologix_gpib_async-1.5.0.dist-info/top_level.txt
prologix_gpib_async-1.5.0.dist-info/RECORD
