Metadata-Version: 2.4
Name: prologix-gpib-async
Version: 1.5.0
Summary: A Python AsyncIO library for the Prologix GPIB (Ethernet) adapter
Author-email: Patrick Baus <patrick.baus@physik.tu-darmstadt.de>
License: GNU General Public License v3 (GPLv3)
Project-URL: Homepage, https://github.com/PatrickBaus/pyAsyncPrologixGpib
Project-URL: Bug Tracker, https://github.com/PatrickBaus/pyAsyncPrologixGpib/issues
Project-URL: Download, https://github.com/PatrickBaus/pyAsyncPrologixGpib/releases
Keywords: Prologix,GPIB,API
Classifier: Programming Language :: Python :: 3
Classifier: Programming Language :: Python :: 3.9
Classifier: Programming Language :: Python :: 3.10
Classifier: Programming Language :: Python :: 3.11
Classifier: Programming Language :: Python :: 3.12
Classifier: Programming Language :: Python :: 3.13
Classifier: Development Status :: 5 - Production/Stable
Classifier: License :: OSI Approved :: GNU General Public License v3 (GPLv3)
Classifier: Operating System :: OS Independent
Classifier: Intended Audience :: Developers
Classifier: Intended Audience :: Science/Research
Classifier: Natural Language :: English
Classifier: Topic :: Home Automation
Classifier: Topic :: Scientific/Engineering
Requires-Python: >=3.7
License-File: LICENSE
Requires-Dist: typing-extensions; python_version < "3.11"
Provides-Extra: dev
Requires-Dist: asyncio_mqtt; extra == "dev"
Requires-Dist: black; extra == "dev"
Requires-Dist: build; extra == "dev"
Requires-Dist: isort; extra == "dev"
Requires-Dist: mypy; extra == "dev"
Requires-Dist: pre-commit; extra == "dev"
Requires-Dist: pylint; extra == "dev"
Requires-Dist: simplejson; extra == "dev"
Requires-Dist: twine; extra == "dev"
Provides-Extra: test
Requires-Dist: asyncio_mqtt; extra == "test"
Requires-Dist: mypy; extra == "test"
Requires-Dist: pylint; extra == "test"
Requires-Dist: pytest; extra == "test"
Requires-Dist: setuptools; extra == "test"
Requires-Dist: simplejson; extra == "test"
Dynamic: license-file
